Workbook

Sheet Instructions
A1: Hospital Resilience Self-Assessment Tool
A2: Based on: Resilient Hospitals - Inter-regional Guidance for Strengthening Resilience to Health Emergencies and Disasters
A4: SCORING SYSTEM
A5: Status | B5: Score | C5: Description
A6: Not Started | B6: 0 | C6: No action taken, not implemented
A7: Partial | B7: 0.5 | C7: In progress, partially implemented, or needs improvement
A8: Completed | B8: 1 | C8: Fully implemented and regularly maintained
A10: HOW TO USE THIS TOOL
A11: 1. Go to the 'Assessment' sheet
A12: 2. For each item, select a status from the dropdown in the 'Status' column
A13: 3. The score will be calculated automatically
A14: 4. Review the 'Evidence of Compliance' column for guidance on what documentation to look for
A15: 5. Add notes in the 'Notes/Comments' column as needed
A16: 6. View the 'Summary' sheet for overall scores and gaps
A18: SCORE INTERPRETATION
A19: Score Range | B19: Rating | C19: Interpretation
A20: 0-25% | B20: Critical | C20: Hospital is highly vulnerable. Immediate action required.
A21: 25-50% | B21: Developing | C21: Basic elements in place. Focus on filling major gaps.
A22: 50-75% | B22: Progressing | C22: Good foundation. Continue building capabilities.
A23: 75-90% | B23: Advanced | C23: Strong resilience framework. Focus on refinement.
A24: 90-100% | B24: Exemplary | C24: Comprehensive resilience achieved. Maintain and share best practices.

Sheet Assessment
A1: # | B1: Phase | C1: Section | D1: Component | E1: Status | F1: Score | G1: Evidence of Compliance | H1: Notes/Comments
A2: 1.1.1 | B2: BEFORE | C2: 1.1 Strategic Risk Assessment | D2: Hospital has conducted a comprehensive hazard identification and risk assessment (HIRA) | F2: =IF(E2="Completed",1,IF(E2="Partial",0.5,0)) | G2: Documented HIRA report; risk register; hazard maps; vulnerability assessment dated within last 2 years
A3: 1.1.2 | B3: BEFORE | C3: 1.1 Strategic Risk Assessment | D3: Risk assessment is based on historical data, community risks, and hospital vulnerability analysis | F3: =IF(E3="Completed",1,IF(E3="Partial",0.5,0)) | G3: Historical incident records; community risk profile; demographic data analysis; local government hazard data
A4: 1.1.3 | B4: BEFORE | C4: 1.1 Strategic Risk Assessment | D4: Hospital has a documented risk profile covering natural, technological, biological, and societal hazards | F4: =IF(E4="Completed",1,IF(E4="Partial",0.5,0)) | G4: Comprehensive risk profile document addressing all four hazard categories; risk matrix showing likelihood and impact
A5: 1.1.4 | B5: BEFORE | C5: 1.1 Strategic Risk Assessment | D5: Risk assessment is updated at least annually or after significant events | F5: =IF(E5="Completed",1,IF(E5="Partial",0.5,0)) | G5: Dated revision history; annual review meeting minutes; post-incident update records
A6: 1.1.5 | B6: BEFORE | C6: 1.1 Strategic Risk Assessment | D6: Risk assessment findings are communicated to hospital leadership and relevant departments | F6: =IF(E6="Completed",1,IF(E6="Partial",0.5,0)) | G6: Leadership briefing records; department head meeting minutes; risk communication memos
A7: 1.1.6 | B7: BEFORE | C7: 1.1 Strategic Risk Assessment | D7: Strategic plans incorporate risk-informed decision making | F7: =IF(E7="Completed",1,IF(E7="Partial",0.5,0)) | G7: Strategic plan with risk considerations; budget allocations for risk mitigation
A8: 1.2.1 | B8: BEFORE | C8: 1.2 Risk Reduction - SPACE | D8: Hospital has completed the Hospital Safety Index (HSI) assessment | F8: =IF(E8="Completed",1,IF(E8="Partial",0.5,0)) | G8: Completed HSI evaluation form; HSI score report; action plan based on HSI findings
A9: 1.2.2 | B9: BEFORE | C9: 1.2 Risk Reduction - SPACE | D9: Structural mitigation measures are implemented based on building vulnerability assessment | F9: =IF(E9="Completed",1,IF(E9="Partial",0.5,0)) | G9: Structural engineering report; seismic/wind retrofitting records; building reinforcement documentation
A10: 1.2.3 | B10: BEFORE | C10: 1.2 Risk Reduction - SPACE | D10: Non-structural elements (equipment, utilities, architectural) are secured against hazards | F10: =IF(E10="Completed",1,IF(E10="Partial",0.5,0)) | G10: Equipment anchoring records; utility protection measures; ceiling/partition securing
A11: 1.2.4 | B11: BEFORE | C11: 1.2 Risk Reduction - SPACE | D11: Hospital meets accessibility standards for persons with disabilities | F11: =IF(E11="Completed",1,IF(E11="Partial",0.5,0)) | G11: Accessibility audit report; ramps and elevators functional; accessible signage
A12: 1.2.5 | B12: BEFORE | C12: 1.2 Risk Reduction - SPACE | D12: Critical infrastructure (power, water, HVAC, medical gases) has redundancy/backup systems | F12: =IF(E12="Completed",1,IF(E12="Partial",0.5,0)) | G12: Backup generator test logs; water storage capacity records; UPS systems documentation
A13: 1.2.6 | B13: BEFORE | C13: 1.2 Risk Reduction - SPACE | D13: Hospital has implemented green/sustainable infrastructure measures | F13: =IF(E13="Completed",1,IF(E13="Partial",0.5,0)) | G13: Solar/renewable energy installations; water recycling systems; SMART hospital assessment
... A142: 3.6.8 | B142: AFTER | C142: 3.6 After Action Review | D142: Lessons learned process with corrective action plan is established | F142: =IF(E142="Completed",1,IF(E142="Partial",0.5,0)) | G142: Lessons learned database; corrective action template; tracking

Sheet Summary
A1: Phase | B1: Section | C1: # Items | D1: Max Score | E1: Your Score | F1: Percentage | G1: Status
A2: BEFORE | B2: 1.1 Strategic Risk Assessment | C2: 6 | D2: 6 | E2: =SUMIF(Assessment!C:C,B2,Assessment!F:F) | F2: =IF(D2>0,E2/D2*100,0) | G2: =IF(F2>=90,"Exemplary",IF(F2>=75,"Advanced",IF(F2>=50,"Progressing",IF(F2>=25,"Developing","Critical"))))
A3: BEFORE | B3: 1.2 Risk Reduction - SPACE | C3: 8 | D3: 8 | E3: =SUMIF(Assessment!C:C,B3,Assessment!F:F) | F3: =IF(D3>0,E3/D3*100,0) | G3: =IF(F3>=90,"Exemplary",IF(F3>=75,"Advanced",IF(F3>=50,"Progressing",IF(F3>=25,"Developing","Critical"))))
A4: BEFORE | B4: 1.3 Risk Reduction - SYSTEMS | C4: 8 | D4: 8 | E4: =SUMIF(Assessment!C:C,B4,Assessment!F:F) | F4: =IF(D4>0,E4/D4*100,0) | G4: =IF(F4>=90,"Exemplary",IF(F4>=75,"Advanced",IF(F4>=50,"Progressing",IF(F4>=25,"Developing","Critical"))))
A5: BEFORE | B5: 1.4 Risk Reduction - STUFF | C5: 6 | D5: 6 | E5: =SUMIF(Assessment!C:C,B5,Assessment!F:F) | F5: =IF(D5>0,E5/D5*100,0) | G5: =IF(F5>=90,"Exemplary",IF(F5>=75,"Advanced",IF(F5>=50,"Progressing",IF(F5>=25,"Developing","Critical"))))
A6: BEFORE | B6: 1.5 Risk Reduction - STAFF | C6: 6 | D6: 6 | E6: =SUMIF(Assessment!C:C,B6,Assessment!F:F) | F6: =IF(D6>0,E6/D6*100,0) | G6: =IF(F6>=90,"Exemplary",IF(F6>=75,"Advanced",IF(F6>=50,"Progressing",IF(F6>=25,"Developing","Critical"))))
A7: BEFORE | B7: 1.6 Preparedness - SPACE | C7: 5 | D7: 5 | E7: =SUMIF(Assessment!C:C,B7,Assessment!F:F) | F7: =IF(D7>0,E7/D7*100,0) | G7: =IF(F7>=90,"Exemplary",IF(F7>=75,"Advanced",IF(F7>=50,"Progressing",IF(F7>=25,"Developing","Critical"))))
A8: BEFORE | B8: 1.7 Preparedness - STRATEGIES | C8: 12 | D8: 12 | E8: =SUMIF(Assessment!C:C,B8,Assessment!F:F) | F8: =IF(D8>0,E8/D8*100,0) | G8: =IF(F8>=90,"Exemplary",IF(F8>=75,"Advanced",IF(F8>=50,"Progressing",IF(F8>=25,"Developing","Critical"))))
A9: BEFORE | B9: 1.8 Preparedness - SYSTEMS | C9: 6 | D9: 6 | E9: =SUMIF(Assessment!C:C,B9,Assessment!F:F) | F9: =IF(D9>0,E9/D9*100,0) | G9: =IF(F9>=90,"Exemplary",IF(F9>=75,"Advanced",IF(F9>=50,"Progressing",IF(F9>=25,"Developing","Critical"))))
A10: BEFORE | B10: 1.9 Preparedness - STUFF | C10: 8 | D10: 8 | E10: =SUMIF(Assessment!C:C,B10,Assessment!F:F) | F10: =IF(D10>0,E10/D10*100,0) | G10: =IF(F10>=90,"Exemplary",IF(F10>=75,"Advanced",IF(F10>=50,"Progressing",IF(F10>=25,"Developing","Critical"))))
A11: BEFORE | B11: 1.10 Preparedness - STAFF | C11: 8 | D11: 8 | E11: =SUMIF(Assessment!C:C,B11,Assessment!F:F) | F11: =IF(D11>0,E11/D11*100,0) | G11: =IF(F11>=90,"Exemplary",IF(F11>=75,"Advanced",IF(F11>=50,"Progressing",IF(F11>=25,"Developing","Critical"))))
A12: DURING | B12: 2.1 Response - SPACE | C12: 4 | D12: 4 | E12: =SUMIF(Assessment!C:C,B12,Assessment!F:F) | F12: =IF(D12>0,E12/D12*100,0) | G12: =IF(F12>=90,"Exemplary",IF(F12>=75,"Advanced",IF(F12>=50,"Progressing",IF(F12>=25,"Developing","Critical"))))
A13: DURING | B13: 2.2 Response - STRATEGIES | C13: 8 | D13: 8 | E13: =SUMIF(Assessment!C:C,B13,Assessment!F:F) | F13: =IF(D13>0,E13/D13*100,0) | G13: =IF(F13>=90,"Exemplary",IF(F13>=75,"Advanced",IF(F13>=50,"Progressing",IF(F13>=25,"Developing","Critical"))))
... A22: AFTER | B22: 3.6 After Action Review | C22: 8 | D22: 8 | E22: =SUMIF(Assessment!C:C,B22,Assessment!F:F) | F22: =IF(D22>0,E22/D22*100,0) | G22: =IF(F22>=90,"Exemplary",IF(F22>=75,"Advanced",IF(F22>=50,"Progressing",IF(F22>=25,"Developing","Critical"))))
A23: TOTAL | C23: =SUM(C2:C22) | D23: =SUM(D2:D22) | E23: =SUM(E2:E22) | F23: =IF(D23>0,E23/D23*100,0) | G23: =IF(F23>=90,"Exemplary",IF(F23>=75,"Advanced",IF(F23>=50,"Progressing",IF(F23>=25,"Developing","Critical"))))
